s7datablock/__init__.py
s7datablock/constants.py
s7datablock/fields.py
s7datablock/grammar.py
s7datablock/mapping.py
s7datablock/parser.py
s7datablock/py.typed
s7datablock-0.0.2.dist-info/METADATA
s7datablock-0.0.2.dist-info/WHEEL
s7datablock-0.0.2.dist-info/licenses/AUTHORS.md
s7datablock-0.0.2.dist-info/licenses/LICENSE.txt
s7datablock-0.0.2.dist-info/RECORD
