Metadata-Version: 2.4
Name: s7datablock
Version: 0.0.2
Summary: A Python library for interacting with Siemens S7 PLC datablocks
Project-URL: Homepage, https://github.com/CEAD-group/s7datablock
Project-URL: Documentation, https://github.com/CEAD-group/s7datablock
Author-email: Thijs Damsma <thijs@damsma.net>
License: MIT
License-File: AUTHORS.md
License-File: LICENSE.txt
Classifier: Development Status :: 4 - Beta
Classifier: Programming Language :: Python
Requires-Python: >=3.11
Requires-Dist: pyparsing
Requires-Dist: python-snap7
Requires-Dist: rich
Provides-Extra: testing
Requires-Dist: pytest; extra == 'testing'
Requires-Dist: pytest-cov; extra == 'testing'
Requires-Dist: ruff; extra == 'testing'
